pidatametrics/__init__.py
pidatametrics/client.py
pidatametrics/exporter.py
pidatametrics/manager.py
pidatametrics/parsers.py
pidatametrics-0.3.3.dist-info/METADATA
pidatametrics-0.3.3.dist-info/WHEEL
pidatametrics-0.3.3.dist-info/RECORD
