Metadata-Version: 2.4
Name: pidatametrics
Version: 0.3.3
Summary: A wrapper for Pi Datametrics API with CSV and BigQuery support.
Requires-Dist: google-cloud-bigquery
Requires-Dist: requests
